README.rst
setup.py
vectormath/__init__.py
vectormath/vector.py
vectormath.egg-info/PKG-INFO
vectormath.egg-info/SOURCES.txt
vectormath.egg-info/dependency_links.txt
vectormath.egg-info/requires.txt
vectormath.egg-info/top_level.txt