Metadata-Version: 1.1
Name: vectormath
Version: 0.1.1
Summary: vectormath
Home-page: https://github.com/3ptscience/vectormath
Author: 3point Science
Author-email: info@3ptscience.com
License: MIT License
Download-URL: http://github.com/3ptscience/vectormath
Keywords: linear algebra,vector,plane,math
Platform: Windows
Platform: Linux
Platform: Solaris
Platform: Mac OS-X
Platform: Unix
Classifier: Development Status :: 4 - Beta
Classifier: Programming Language :: Python
Classifier: Topic :: Scientific/Engineering
Classifier: Topic :: Scientific/Engineering :: Mathematics
Classifier: Topic :: Scientific/Engineering :: Physics
Classifier: Operating System :: Microsoft :: Windows
Classifier: Operating System :: POSIX
Classifier: Operating System :: Unix
Classifier: Operating System :: MacOS
Classifier: Natural Language :: English
